phylia/__init__.py
phylia/_core/__init__.py
phylia/_core/_releve.py
phylia/data/__init__.py
phylia/data/_syntaxa.py
phylia/data/_taxa.py
phylia/data/_turboveg.py
phylia/data/beheertypen_kenmerkendheid.csv
phylia/data/definition_remarks.csv
phylia/data/definition_tvabund.csv
phylia/data/definition_tvhabita.csv
phylia/data/mapped_areas.JPG
phylia/data/sbbcat_syntaxonnames.csv
phylia/data/synbiosys_soorten_2017.csv
phylia/data/synbiosys_syntaxa_2017.csv
phylia/data/synbiosys_syntaxa_metadata2017.csv
phylia/data/synbiosys_syntaxa_tabellen2017.csv
phylia/plot/__init__.py
phylia/plot/_sankey_two_maps.py
phylia/read/__init__.py
phylia/read/_mdb.py
phylia/read/_shapefile.py
phylia/read/_tv2db.py
phylia/read/_tvxml.py
phylia/sample/__init__.py
phylia/sample/_samplepolygonmap.py
phylia/sbb/__init__.py
phylia/sbb/_mapdata.py
phylia/sbb/_mapelements.py
phylia/sbb/_maptables.py
phylia/tools/__init__.py
phylia/tools/_conversions.py
phylia/tools/_filetools.py
phylia/tools/_projectstable.py
phylia/tools/_syntaxontools.py
phylia/tools/_write_excel.py
phylia-0.0.3.dist-info/LICENSE
phylia-0.0.3.dist-info/METADATA
phylia-0.0.3.dist-info/WHEEL
phylia-0.0.3.dist-info/top_level.txt
phylia-0.0.3.dist-info/RECORD
