Metadata-Version: 2.1
Name: phylia
Version: 0.0.3
Summary: phylia is a python package for phytosociological information analysis.
Author-email: Thomas de Meij <mailphylia@gmail.com>
Project-URL: Homepage, https://github.com/phylia-project/phylia.git
Project-URL: Issues, https://github.com/phylia-project/phylia/issues
Classifier: Programming Language :: Python :: 3
Classifier: License :: OSI Approved :: GNU General Public License v3 (GPLv3)
Classifier: Operating System :: Microsoft :: Windows :: Windows 11
Requires-Python: >=3.10
License-File: LICENSE
Requires-Dist: geopandas
Requires-Dist: numpy
Requires-Dist: pandas
Requires-Dist: matplotlib
Requires-Dist: pyodbc
Requires-Dist: lxml
Requires-Dist: plotly
